{
    "IN": "Pakistan",
    "US": "Canada",
    "CA": "United States of America",
    "GB": "Ireland",
    "FR": "Germany",
    "DE": "Poland",
    "JP": "South Korea",
    "CN": "Russia",
    "AU": "New Zealand",
    "BR": "Argentina",
    "ZA": "Botswana",
    "IT": "France",
    "ES": "Portugal",
    "RU": "China",
    "MX": "United States of America",
    "KR": "Japan",
    "AR": "Chile",
    "SA": "United Arab Emirates",
    "AE": "Saudi Arabia",
    "SG": "Malaysia",
    "SE": "Norway",
    "CH": "Germany",
    "NL": "Belgium",
    "NZ": "Australia",
    "BE": "Netherlands",
    "PL": "Germany",
    "PT": "Spain",
    "TR": "Greece",
    "ID": "Malaysia"
}
